uclient/__init__.py
uclient/_constants.py
uclient/async_client.py
uclient/sync_client.py
uclient/types/_base.py
uclient/types/errors.py
uclient/types/request.py
uclient/types/response.py
uclient-0.1.0.dist-info/METADATA
uclient-0.1.0.dist-info/WHEEL
uclient-0.1.0.dist-info/RECORD
